README.md
setup.cfg
setup.py
src/pybanking/__init__.py
src/pybanking.egg-info/PKG-INFO
src/pybanking.egg-info/SOURCES.txt
src/pybanking.egg-info/dependency_links.txt
src/pybanking.egg-info/requires.txt
src/pybanking.egg-info/top_level.txt
src/pybanking/EDA/__init__.py
src/pybanking/EDA/data_analysis.py
src/pybanking/churn_prediction/__init__.py
src/pybanking/churn_prediction/model_churn.py
src/pybanking/deposit_prediction/__init__.py
src/pybanking/deposit_prediction/model_banking_deposit.py
src/pybanking/example/__init__.py
src/pybanking/example/custom_sklearn.py
src/pybanking/transaction_prediction/__init__.py
src/pybanking/transaction_prediction/model_transaction.py
src/pybanking/value_prediction/__init__.py
src/pybanking/value_prediction/model_value_prediction.py