Metadata-Version: 2.1
Name: pybanking
Version: 1.1.2
Summary: Machine learning module for banking
Home-page: https://github.com/shorthillstech/pybanking
Author: Shorthills Tech
Author-email: apurv@shorthillstech.com
License: MIT
Keywords: banking project
Platform: UNKNOWN
